provider/__init__.py
provider/amazon.py
provider/cloud_provider.py
provider/google.py
envvar_manager-0.1.dist-info/METADATA
envvar_manager-0.1.dist-info/WHEEL
envvar_manager-0.1.dist-info/entry_points.txt
envvar_manager-0.1.dist-info/top_level.txt
envvar_manager-0.1.dist-info/RECORD
