Metadata-Version: 2.1
Name: envvar-manager
Version: 0.1
Author: Omer Gindes
Author-email: omer.gindes@gmail.com
Requires-Dist: google-cloud-storage
Requires-Dist: boto3
Requires-Dist: python-dotenv
Requires-Dist: click
